{
    "app": {
        "name": "نظام إدارة النادي الرياضي",
        "tagline": "إدارة احترافية للنادي"
    },
    "nav": {
        "dashboard": "لوحة التحكم",
        "members": "الأعضاء",
        "subscriptions": "الاشتراكات",
        "checkin": "تسجيل الدخول",
        "payments": "المدفوعات",
        "reports": "التقارير",
        "settings": "الإعدادات",
        "plans": "الخطط"
    },
    "auth": {
        "login": "تسجيل الدخول",
        "logout": "تسجيل الخروج",
        "username": "اسم المستخدم",
        "password": "كلمة المرور",
        "rememberMe": "تذكرني",
        "forgotPassword": "نسيت كلمة المرور؟",
        "loginButton": "دخول",
        "loginSuccess": "مرحباً بعودتك!",
        "loginError": "اسم المستخدم أو كلمة المرور غير صحيحة",
        "logoutSuccess": "تم تسجيل الخروج بنجاح"
    },
    "dashboard": {
        "title": "لوحة التحكم",
        "welcome": "مرحباً بعودتك",
        "totalMembers": "إجمالي الأعضاء",
        "activeMembers": "الأعضاء النشطين",
        "expiringSubscriptions": "اشتراكات تنتهي قريباً",
        "todayCheckIns": "تسجيلات اليوم",
        "monthlyRevenue": "إيرادات الشهر",
        "todayRevenue": "إيرادات اليوم",
        "recentMembers": "الأعضاء الجدد",
        "recentPayments": "أحدث المدفوعات",
        "recentCheckIns": "آخر تسجيلات الدخول",
        "viewAll": "عرض الكل",
        "aiInsights": "رؤى ذكية",
        "inactiveMembers": "أعضاء غير نشطين"
    },
    "members": {
        "title": "الأعضاء",
        "addMember": "إضافة عضو",
        "editMember": "تعديل العضو",
        "memberDetails": "تفاصيل العضو",
        "searchPlaceholder": "بحث عن الأعضاء...",
        "firstName": "الاسم الأول",
        "lastName": "اسم العائلة",
        "email": "البريد الإلكتروني",
        "phone": "الهاتف",
        "gender": "الجنس",
        "male": "ذكر",
        "female": "أنثى",
        "dateOfBirth": "تاريخ الميلاد",
        "address": "العنوان",
        "emergencyContact": "جهة اتصال الطوارئ",
        "emergencyPhone": "هاتف الطوارئ",
        "joinDate": "تاريخ الانضمام",
        "status": "الحالة",
        "active": "نشط",
        "inactive": "غير نشط",
        "notes": "ملاحظات",
        "photo": "الصورة",
        "uploadPhoto": "رفع صورة",
        "qrCode": "رمز QR",
        "noMembers": "لا يوجد أعضاء",
        "confirmDelete": "هل أنت متأكد من حذف هذا العضو؟",
        "memberCreated": "تم إنشاء العضو بنجاح",
        "memberUpdated": "تم تحديث العضو بنجاح",
        "memberDeleted": "تم حذف العضو بنجاح"
    },
    "subscriptions": {
        "title": "الاشتراكات",
        "plans": "خطط الاشتراك",
        "addPlan": "إضافة خطة",
        "assignSubscription": "تعيين اشتراك",
        "planName": "اسم الخطة",
        "duration": "المدة",
        "price": "السعر",
        "features": "المميزات",
        "startDate": "تاريخ البدء",
        "endDate": "تاريخ الانتهاء",
        "daysRemaining": "الأيام المتبقية",
        "status": "الحالة",
        "active": "نشط",
        "expired": "منتهي",
        "expiring": "ينتهي قريباً",
        "frozen": "مجمد",
        "cancelled": "ملغي",
        "renew": "تجديد",
        "freeze": "تجميد",
        "unfreeze": "إلغاء التجميد",
        "cancel": "إلغاء",
        "noSubscription": "لا يوجد اشتراك نشط",
        "member": "العضو",
        "contact": "جهة الاتصال",
        "plan": "الخطة",
        "dates": "التواريخ",
        "remaining": "المتبقي",
        "paymentStatus": "حالة الدفع",
        "renewSubscription": "تجديد الاشتراك",
        "startNewPlan": "بدء خطة جديدة",
        "renewalNote": "ستبدأ الخطة الجديدة بعد انتهاء الخطة الحالية، أو فوراً إذا كانت منتهية.",
        "confirmRenewal": "تأكيد التجديد",
        "renewedToday": "تم التجديد اليوم"
    },
    "checkin": {
        "title": "محطة تسجيل الدخول",
        "scanQR": "مسح رمز QR",
        "faceRecognition": "التعرف على الوجه",
        "manual": "إدخال يدوي",
        "enterMemberId": "أدخل رقم العضوية",
        "checkIn": "تسجيل دخول",
        "checkOut": "تسجيل خروج",
        "success": "تم تسجيل الدخول بنجاح!",
        "welcome": "مرحباً",
        "todayAttendance": "حضور اليوم",
        "activeNow": "متواجدون الآن",
        "history": "سجل الحضور"
    },
    "payments": {
        "title": "المدفوعات",
        "recordPayment": "تسجيل دفعة",
        "amount": "المبلغ",
        "method": "طريقة الدفع",
        "cash": "نقدي",
        "card": "بطاقة",
        "transfer": "تحويل بنكي",
        "receipt": "إيصال",
        "downloadReceipt": "تحميل الإيصال",
        "paymentRecorded": "تم تسجيل الدفعة بنجاح",
        "totalRevenue": "إجمالي الإيرادات",
        "noPayments": "لا توجد مدفوعات"
    },
    "reports": {
        "title": "التقارير",
        "memberReport": "تقرير الأعضاء",
        "revenueReport": "تقرير الإيرادات",
        "attendanceReport": "تقرير الحضور",
        "subscriptionReport": "تقرير الاشتراكات",
        "export": "تصدير",
        "exportExcel": "تصدير إلى Excel",
        "dateRange": "نطاق التاريخ",
        "from": "من تاريخ ووقت",
        "to": "إلى تاريخ ووقت",
        "generate": "إنشاء التقرير",
        "summary": "الملخص",
        "fields": {
            "totalRevenue": "إجمالي الإيرادات",
            "paymentCount": "عدد المدفوعات",
            "totalCheckIns": "إجمالي الحضور",
            "total": "الإجمالي",
            "active": "نشط",
            "withSubscription": "لديه اشتراك",
            "receiptNumber": "رقم الإيصال",
            "memberId": "رقم العضوية",
            "memberName": "اسم العضو",
            "firstName": "الاسم الأول",
            "lastName": "اسم العائلة",
            "email": "البريد الإلكتروني",
            "phone": "الهاتف",
            "planName": "اسم الخطة",
            "amount": "المبلغ",
            "method": "الطريقة",
            "paidAt": "التاريخ",
            "checkIn": "وقت الدخول",
            "checkOut": "وقت الخروج",
            "duration": "المدة",
            "startDate": "تاريخ البدء",
            "endDate": "تاريخ الانتهاء",
            "status": "الحالة",
            "paidAmount": "المبلغ المدفوع",
            "gender": "الجنس"
        }
    },
    "settings": {
        "title": "الإعدادات",
        "general": "عام",
        "branding": "العلامة التجارية",
        "pricing": "التسعير",
        "backup": "النسخ الاحتياطي",
        "license": "الترخيص",
        "gymName": "اسم النادي",
        "gymPhone": "الهاتف",
        "gymEmail": "البريد الإلكتروني",
        "gymAddress": "العنوان",
        "currency": "العملة",
        "language": "اللغة",
        "theme": "المظهر",
        "darkMode": "الوضع الداكن",
        "lightMode": "الوضع الفاتح",
        "primaryColor": "اللون الرئيسي",
        "logo": "الشعار",
        "uploadLogo": "رفع الشعار",
        "saved": "تم حفظ الإعدادات بنجاح"
    },
    "plans": {
        "title": "إدارة الخطط",
        "addPlan": "إضافة خطة",
        "editPlan": "تعديل الخطة",
        "name": "اسم الخطة",
        "duration": "المدة",
        "price": "السعر",
        "active": "نشط",
        "inactive": "غير نشط",
        "status": "الحالة",
        "actions": "إجراءات",
        "confirmDelete": "هل أنت متأكد من حذف هذه الخطة؟",
        "planCreated": "تم إنشاء الخطة بنجاح",
        "planUpdated": "تم تحديث الخطة بنجاح",
        "planDeleted": "تم حذف الخطة بنجاح"
    },
    "backup": {
        "title": "النسخ الاحتياطي والاستعادة",
        "createBackup": "إنشاء نسخة احتياطية",
        "restore": "استعادة",
        "download": "تحميل",
        "delete": "حذف",
        "lastBackup": "آخر نسخة احتياطية",
        "backupCreated": "تم إنشاء النسخة الاحتياطية بنجاح",
        "restoreWarning": "سيتم استبدال جميع البيانات الحالية. هل أنت متأكد؟",
        "restoreSuccess": "تم الاستعادة بنجاح. يرجى إعادة تشغيل التطبيق."
    },
    "license": {
        "title": "الترخيص",
        "status": "حالة الترخيص",
        "valid": "صالح",
        "expired": "منتهي",
        "invalid": "غير صالح",
        "type": "نوع الترخيص",
        "expiresAt": "ينتهي في",
        "daysRemaining": "الأيام المتبقية",
        "activateLicense": "تفعيل الترخيص",
        "enterKey": "أدخل مفتاح الترخيص",
        "activate": "تفعيل",
        "activated": "تم تفعيل الترخيص بنجاح"
    },
    "common": {
        "save": "حفظ",
        "cancel": "إلغاء",
        "delete": "حذف",
        "edit": "تعديل",
        "add": "إضافة",
        "search": "بحث",
        "filter": "تصفية",
        "export": "تصدير",
        "import": "استيراد",
        "loading": "جاري التحميل...",
        "noData": "لا توجد بيانات",
        "confirm": "تأكيد",
        "yes": "نعم",
        "no": "لا",
        "success": "نجاح",
        "error": "خطأ",
        "warning": "تحذير",
        "info": "معلومات",
        "actions": "إجراءات",
        "view": "عرض",
        "back": "رجوع",
        "next": "التالي",
        "previous": "السابق",
        "page": "صفحة",
        "of": "من",
        "showing": "عرض",
        "to": "إلى",
        "entries": "سجلات",
        "all": "الكل",
        "none": "لا شيء",
        "today": "اليوم",
        "yesterday": "أمس",
        "thisWeek": "هذا الأسبوع",
        "thisMonth": "هذا الشهر",
        "thisYear": "هذا العام"
    },
    "errors": {
        "required": "هذا الحقل مطلوب",
        "invalidEmail": "البريد الإلكتروني غير صالح",
        "invalidPhone": "رقم الهاتف غير صالح",
        "minLength": "الحد الأدنى {{count}} أحرف",
        "maxLength": "الحد الأقصى {{count}} أحرف",
        "serverError": "خطأ في الخادم. يرجى المحاولة مرة أخرى.",
        "networkError": "خطأ في الشبكة. يرجى التحقق من الاتصال."
    },
    "cashClosing": {
        "title": "تقفيل الكاش",
        "createClosing": "إنشاء تقفيل",
        "viewClosings": "عرض التقفيلات",
        "employee": "الموظف",
        "allEmployees": "جميع الموظفين",
        "period": "الفترة",
        "periodType": {
            "daily": "يومي",
            "monthly": "شهري",
            "custom": "مخصص",
            "shift": "وردية"
        },
        "expectedCash": "المتوقع نقدي",
        "expectedNonCash": "المتوقع غير نقدي",
        "expectedTotal": "المتوقع الإجمالي",
        "declaredCash": "المعلن نقدي",
        "declaredNonCash": "المعلن غير نقدي",
        "declaredTotal": "المعلن الإجمالي",
        "differenceCash": "الفرق نقدي",
        "differenceNonCash": "الفرق غير نقدي",
        "differenceTotal": "الفرق الإجمالي",
        "status": {
            "shortage": "عجز",
            "overage": "زيادة",
            "balanced": "متوازن"
        },
        "immutableWarning": "⚠️ لا يمكن تعديل التقفيل بعد الحفظ",
        "confirmCreate": "تأكيد الإنشاء",
        "closingCreated": "تم إنشاء التقفيل بنجاح",
        "closingFailed": "فشل إنشاء التقفيل",
        "noClosings": "لا توجد تقفيلات",
        "summary": "الملخص",
        "notes": "ملاحظات",
        "createdBy": "تم الإنشاء بواسطة",
        "createdAt": "تاريخ الإنشاء"
    }
}